odoo/addons/shopfloor_vendor_packaging/README.rst
odoo/addons/shopfloor_vendor_packaging/__init__.py
odoo/addons/shopfloor_vendor_packaging/__manifest__.py
odoo/addons/shopfloor_vendor_packaging/actions/__init__.py
odoo/addons/shopfloor_vendor_packaging/actions/data.py
odoo/addons/shopfloor_vendor_packaging/i18n/it.po
odoo/addons/shopfloor_vendor_packaging/i18n/shopfloor_vendor_packaging.pot
odoo/addons/shopfloor_vendor_packaging/models/__init__.py
odoo/addons/shopfloor_vendor_packaging/models/shopfloor_menu.py
odoo/addons/shopfloor_vendor_packaging/readme/CONTRIBUTORS.md
odoo/addons/shopfloor_vendor_packaging/readme/DESCRIPTION.md
odoo/addons/shopfloor_vendor_packaging/static/description/icon.png
odoo/addons/shopfloor_vendor_packaging/static/description/index.html
odoo/addons/shopfloor_vendor_packaging/tests/__init__.py
odoo/addons/shopfloor_vendor_packaging/tests/test_shopfloor_vendor_packaging.py
odoo/addons/shopfloor_vendor_packaging/views/shopfloor_menu.xml
odoo_addon_shopfloor_vendor_packaging-18.0.1.0.0.2.dist-info/METADATA
odoo_addon_shopfloor_vendor_packaging-18.0.1.0.0.2.dist-info/WHEEL
odoo_addon_shopfloor_vendor_packaging-18.0.1.0.0.2.dist-info/top_level.txt
odoo_addon_shopfloor_vendor_packaging-18.0.1.0.0.2.dist-info/RECORD
